logging_middleware/__init__.py
logging_middleware/checks.py
logging_middleware/middlewares.py
logging_middleware/settings.py
django_logging_middleware-0.1.2.dist-info/LICENSE
django_logging_middleware-0.1.2.dist-info/METADATA
django_logging_middleware-0.1.2.dist-info/WHEEL
django_logging_middleware-0.1.2.dist-info/top_level.txt
django_logging_middleware-0.1.2.dist-info/RECORD
