Metadata-Version: 2.1
Name: django-logging-middleware
Version: 0.1.2
Summary: A small package to log django requests and responses
Home-page: https://github.com/fearsd/django-logging-middleware
Author: Rifat Fazlutdinov
Author-email: rifatfazlutdinov@gmail.com
License: UNKNOWN
Platform: UNKNOWN
Classifier: Programming Language :: Python :: 3
Classifier: License :: OSI Approved :: MIT License
Classifier: Operating System :: OS Independent
Classifier: Development Status :: 4 - Beta
Classifier: Environment :: Web Environment
Classifier: Framework :: Django :: 3.0
Classifier: Framework :: Django :: 3.1
Requires-Python: >=3.6
Requires-Dist: django (>=3.0)
Requires-Dist: loguru
